difido_definitions.py
difido/__init__.py
difido/config.py
difido/difido.jar
difido/execution.py
difido/execution_details.py
difido/local_utils.py
difido/plugin.py
difido/remote_utils.py
difido/report_manager.py
difido/reporters.py
difido/test_details.py
pytest_difido-0.5.1.dist-info/LICENSE
pytest_difido-0.5.1.dist-info/METADATA
pytest_difido-0.5.1.dist-info/WHEEL
pytest_difido-0.5.1.dist-info/entry_points.txt
pytest_difido-0.5.1.dist-info/top_level.txt
pytest_difido-0.5.1.dist-info/RECORD
