Metadata-Version: 2.1
Name: pytest-difido
Version: 0.5.1
Summary: PyTest plugin for generating Difido reports
Home-page: https://github.com/Top-Q/difido-reports/tree/master/binders/difido-pytest-plugin/pytest-difido
Author: Itai Agmon
Author-email: itai.agmon@gmail.com
Maintainer: Itai Agmon
Maintainer-email: itai.agmon@gmail.com
License: Apache Software License 2.0
Classifier: Development Status :: 4 - Beta
Classifier: Framework :: Pytest
Classifier: Intended Audience :: Developers
Classifier: Topic :: Software Development :: Testing
Classifier: Programming Language :: Python
Classifier: Programming Language :: Python :: 3
Classifier: Programming Language :: Python :: 3.5
Classifier: Programming Language :: Python :: 3.6
Classifier: Programming Language :: Python :: 3.7
Classifier: Programming Language :: Python :: 3.8
Classifier: Programming Language :: Python :: 3 :: Only
Classifier: Programming Language :: Python :: Implementation :: CPython
Classifier: Programming Language :: Python :: Implementation :: PyPy
Classifier: Operating System :: OS Independent
Classifier: License :: OSI Approved :: Apache Software License
Requires-Python: >=3.5
License-File: LICENSE
Requires-Dist: pytest (>=4.0.0)
Requires-Dist: requests (>=2.20.0)
Requires-Dist: requests-toolbelt (>=0.8.0)
Requires-Dist: rich (>=10.14.0)
